{"nodes": [{"id": "d_bharatheeyam_books_lib_screens_reader_screen_dart", "label": "reader_screen.dart", "file_type": "code", "source_file": "lib/screens/reader_screen.dart", "source_location": null}, {"id": "screens_reader_screen_readerscreen", "label": "ReaderScreen", "file_type": "code", "source_file": "lib/screens/reader_screen.dart", "source_location": null}, {"id": "statelesswidget", "label": "StatelessWidget", "file_type": "code", "source_file": null, "source_location": null}, {"id": "bookmarkservice", "label": "BookmarkService", "file_type": "code", "source_file": null, "source_location": null}, {"id": "screens_reader_screen_stotra", "label": "stotra", "file_type": "code", "source_file": "lib/screens/reader_screen.dart", "source_location": null}, {"id": "stotra", "label": "Stotra", "file_type": "code", "source_file": null, "source_location": null}, {"id": "screens_reader_screen_build", "label": "build", "file_type": "code", "source_file": "lib/screens/reader_screen.dart", "source_location": null}, {"id": "package_flutter_material_dart", "label": "package:flutter/material.dart", "file_type": "code", "source_file": null, "source_location": null}, {"id": "package_provider_provider_dart", "label": "package:provider/provider.dart", "file_type": "code", "source_file": null, "source_location": null}, {"id": "package_google_fonts_google_fonts_dart", "label": "package:google_fonts/google_fonts.dart", "file_type": "code", "source_file": null, "source_location": null}, {"id": "models_stotra_dart", "label": "../models/stotra.dart", "file_type": "code", "source_file": null, "source_location": null}, {"id": "services_bookmark_service_dart", "label": "../services/bookmark_service.dart", "file_type": "code", "source_file": null, "source_location": null}], "edges": [{"source": "d_bharatheeyam_books_lib_screens_reader_screen_dart", "target": "screens_reader_screen_readerscreen", "relation": "defines", "confidence": "EXTRACTED", "confidence_score": 1.0, "source_file": "lib/screens/reader_screen.dart", "source_location": null, "weight": 1.0}, {"source": "screens_reader_screen_readerscreen", "target": "statelesswidget", "relation": "inherits", "confidence": "EXTRACTED", "confidence_score": 1.0, "source_file": "lib/screens/reader_screen.dart", "source_location": null, "weight": 1.0}, {"source": "screens_reader_screen_readerscreen", "target": "bookmarkservice", "relation": "references", "confidence": "EXTRACTED", "confidence_score": 1.0, "source_file": "lib/screens/reader_screen.dart", "source_location": null, "weight": 1.0, "context": "bloc_lookup"}, {"source": "d_bharatheeyam_books_lib_screens_reader_screen_dart", "target": "screens_reader_screen_stotra", "relation": "defines", "confidence": "EXTRACTED", "confidence_score": 1.0, "source_file": "lib/screens/reader_screen.dart", "source_location": null, "weight": 1.0}, {"source": "d_bharatheeyam_books_lib_screens_reader_screen_dart", "target": "stotra", "relation": "references", "confidence": "EXTRACTED", "confidence_score": 1.0, "source_file": "lib/screens/reader_screen.dart", "source_location": null, "weight": 1.0, "context": "variable_type"}, {"source": "d_bharatheeyam_books_lib_screens_reader_screen_dart", "target": "screens_reader_screen_build", "relation": "defines", "confidence": "EXTRACTED", "confidence_score": 1.0, "source_file": "lib/screens/reader_screen.dart", "source_location": null, "weight": 1.0}, {"source": "screens_reader_screen_build", "target": "bookmarkservice", "relation": "references", "confidence": "EXTRACTED", "confidence_score": 1.0, "source_file": "lib/screens/reader_screen.dart", "source_location": null, "weight": 1.0, "context": "bloc_lookup"}, {"source": "d_bharatheeyam_books_lib_screens_reader_screen_dart", "target": "package_flutter_material_dart", "relation": "imports", "confidence": "EXTRACTED", "confidence_score": 1.0, "source_file": "lib/screens/reader_screen.dart", "source_location": null, "weight": 1.0}, {"source": "d_bharatheeyam_books_lib_screens_reader_screen_dart", "target": "package_provider_provider_dart", "relation": "imports", "confidence": "EXTRACTED", "confidence_score": 1.0, "source_file": "lib/screens/reader_screen.dart", "source_location": null, "weight": 1.0}, {"source": "d_bharatheeyam_books_lib_screens_reader_screen_dart", "target": "package_google_fonts_google_fonts_dart", "relation": "imports", "confidence": "EXTRACTED", "confidence_score": 1.0, "source_file": "lib/screens/reader_screen.dart", "source_location": null, "weight": 1.0}, {"source": "d_bharatheeyam_books_lib_screens_reader_screen_dart", "target": "models_stotra_dart", "relation": "imports", "confidence": "EXTRACTED", "confidence_score": 1.0, "source_file": "lib/screens/reader_screen.dart", "source_location": null, "weight": 1.0}, {"source": "d_bharatheeyam_books_lib_screens_reader_screen_dart", "target": "services_bookmark_service_dart", "relation": "imports", "confidence": "EXTRACTED", "confidence_score": 1.0, "source_file": "lib/screens/reader_screen.dart", "source_location": null, "weight": 1.0}, {"source": "d_bharatheeyam_books_lib_screens_reader_screen_dart", "target": "bookmarkservice", "relation": "references", "confidence": "EXTRACTED", "confidence_score": 1.0, "source_file": "lib/screens/reader_screen.dart", "source_location": null, "weight": 1.0, "context": "type_lookup"}]}