{"nodes": [{"id": "d_bharatheeyam_books_lib_services_bookmark_service_dart", "label": "bookmark_service.dart", "file_type": "code", "source_file": "lib/services/bookmark_service.dart", "source_location": null}, {"id": "services_bookmark_service_bookmarkservice", "label": "BookmarkService", "file_type": "code", "source_file": "lib/services/bookmark_service.dart", "source_location": null}, {"id": "changenotifier", "label": "ChangeNotifier", "file_type": "code", "source_file": null, "source_location": null}, {"id": "services_bookmark_service_storagekey", "label": "_storageKey", "file_type": "code", "source_file": "lib/services/bookmark_service.dart", "source_location": null}, {"id": "static_const", "label": "static const", "file_type": "code", "source_file": null, "source_location": null}, {"id": "services_bookmark_service_themekey", "label": "_themeKey", "file_type": "code", "source_file": "lib/services/bookmark_service.dart", "source_location": null}, {"id": "services_bookmark_service_fontsizekey", "label": "_fontSizeKey", "file_type": "code", "source_file": "lib/services/bookmark_service.dart", "source_location": null}, {"id": "services_bookmark_service_bookmarks", "label": "_bookmarks", "file_type": "code", "source_file": "lib/services/bookmark_service.dart", "source_location": null}, {"id": "map", "label": "Map", "file_type": "code", "source_file": null, "source_location": null}, {"id": "services_bookmark_service_isdarkmode", "label": "_isDarkMode", "file_type": "code", "source_file": "lib/services/bookmark_service.dart", "source_location": null}, {"id": "services_bookmark_service_fontscale", "label": "_fontScale", "file_type": "code", "source_file": "lib/services/bookmark_service.dart", "source_location": null}, {"id": "bool_get", "label": "bool get", "file_type": "code", "source_file": null, "source_location": null}, {"id": "double_get", "label": "double get", "file_type": "code", "source_file": null, "source_location": null}, {"id": "services_bookmark_service_count", "label": "count", "file_type": "code", "source_file": "lib/services/bookmark_service.dart", "source_location": null}, {"id": "int_get", "label": "int get", "file_type": "code", "source_file": null, "source_location": null}, {"id": "services_bookmark_service_init", "label": "init", "file_type": "code", "source_file": "lib/services/bookmark_service.dart", "source_location": null}, {"id": "services_bookmark_service_isbookmarked", "label": "isBookmarked", "file_type": "code", "source_file": "lib/services/bookmark_service.dart", "source_location": null}, {"id": "services_bookmark_service_toggle", "label": "toggle", "file_type": "code", "source_file": "lib/services/bookmark_service.dart", "source_location": null}, {"id": "services_bookmark_service_getsavedshlokas", "label": "getSavedShlokas", "file_type": "code", "source_file": "lib/services/bookmark_service.dart", "source_location": null}, {"id": "services_bookmark_service_clearall", "label": "clearAll", "file_type": "code", "source_file": "lib/services/bookmark_service.dart", "source_location": null}, {"id": "services_bookmark_service_exportasjson", "label": "exportAsJson", "file_type": "code", "source_file": "lib/services/bookmark_service.dart", "source_location": null}, {"id": "services_bookmark_service_toggletheme", "label": "toggleTheme", "file_type": "code", "source_file": "lib/services/bookmark_service.dart", "source_location": null}, {"id": "services_bookmark_service_setfontscale", "label": "setFontScale", "file_type": "code", "source_file": "lib/services/bookmark_service.dart", "source_location": null}, {"id": "services_bookmark_service_save", "label": "_save", "file_type": "code", "source_file": "lib/services/bookmark_service.dart", "source_location": null}, {"id": "dart_convert", "label": "dart:convert", "file_type": "code", "source_file": null, "source_location": null}, {"id": "package_flutter_foundation_dart", "label": "package:flutter/foundation.dart", "file_type": "code", "source_file": null, "source_location": null}, {"id": "package_shared_preferences_shared_preferences_dart", "label": "package:shared_preferences/shared_preferences.dart", "file_type": "code", "source_file": null, "source_location": null}, {"id": "models_shloka_dart", "label": "../models/shloka.dart", "file_type": "code", "source_file": null, "source_location": null}], "edges": [{"source": "d_bharatheeyam_books_lib_services_bookmark_service_dart", "target": "services_bookmark_service_bookmarkservice", "relation": "defines", "confidence": "EXTRACTED", "confidence_score": 1.0, "source_file": "lib/services/bookmark_service.dart", "source_location": null, "weight": 1.0}, {"source": "services_bookmark_service_bookmarkservice", "target": "changenotifier", "relation": "inherits", "confidence": "EXTRACTED", "confidence_score": 1.0, "source_file": "lib/services/bookmark_service.dart", "source_location": null, "weight": 1.0}, {"source": "d_bharatheeyam_books_lib_services_bookmark_service_dart", "target": "services_bookmark_service_storagekey", "relation": "defines", "confidence": "EXTRACTED", "confidence_score": 1.0, "source_file": "lib/services/bookmark_service.dart", "source_location": null, "weight": 1.0}, {"source": "d_bharatheeyam_books_lib_services_bookmark_service_dart", "target": "static_const", "relation": "references", "confidence": "EXTRACTED", "confidence_score": 1.0, "source_file": "lib/services/bookmark_service.dart", "source_location": null, "weight": 1.0, "context": "variable_type"}, {"source": "d_bharatheeyam_books_lib_services_bookmark_service_dart", "target": "services_bookmark_service_themekey", "relation": "defines", "confidence": "EXTRACTED", "confidence_score": 1.0, "source_file": "lib/services/bookmark_service.dart", "source_location": null, "weight": 1.0}, {"source": "d_bharatheeyam_books_lib_services_bookmark_service_dart", "target": "static_const", "relation": "references", "confidence": "EXTRACTED", "confidence_score": 1.0, "source_file": "lib/services/bookmark_service.dart", "source_location": null, "weight": 1.0, "context": "variable_type"}, {"source": "d_bharatheeyam_books_lib_services_bookmark_service_dart", "target": "services_bookmark_service_fontsizekey", "relation": "defines", "confidence": "EXTRACTED", "confidence_score": 1.0, "source_file": "lib/services/bookmark_service.dart", "source_location": null, "weight": 1.0}, {"source": "d_bharatheeyam_books_lib_services_bookmark_service_dart", "target": "static_const", "relation": "references", "confidence": "EXTRACTED", "confidence_score": 1.0, "source_file": "lib/services/bookmark_service.dart", "source_location": null, "weight": 1.0, "context": "variable_type"}, {"source": "d_bharatheeyam_books_lib_services_bookmark_service_dart", "target": "services_bookmark_service_bookmarks", "relation": "defines", "confidence": "EXTRACTED", "confidence_score": 1.0, "source_file": "lib/services/bookmark_service.dart", "source_location": null, "weight": 1.0}, {"source": "d_bharatheeyam_books_lib_services_bookmark_service_dart", "target": "map", "relation": "references", "confidence": "EXTRACTED", "confidence_score": 1.0, "source_file": "lib/services/bookmark_service.dart", "source_location": null, "weight": 1.0, "context": "variable_type"}, {"source": "d_bharatheeyam_books_lib_services_bookmark_service_dart", "target": "services_bookmark_service_isdarkmode", "relation": "defines", "confidence": "EXTRACTED", "confidence_score": 1.0, "source_file": "lib/services/bookmark_service.dart", "source_location": null, "weight": 1.0}, {"source": "d_bharatheeyam_books_lib_services_bookmark_service_dart", "target": "services_bookmark_service_fontscale", "relation": "defines", "confidence": "EXTRACTED", "confidence_score": 1.0, "source_file": "lib/services/bookmark_service.dart", "source_location": null, "weight": 1.0}, {"source": "d_bharatheeyam_books_lib_services_bookmark_service_dart", "target": "services_bookmark_service_bookmarks", "relation": "defines", "confidence": "EXTRACTED", "confidence_score": 1.0, "source_file": "lib/services/bookmark_service.dart", "source_location": null, "weight": 1.0}, {"source": "d_bharatheeyam_books_lib_services_bookmark_service_dart", "target": "map", "relation": "references", "confidence": "EXTRACTED", "confidence_score": 1.0, "source_file": "lib/services/bookmark_service.dart", "source_location": null, "weight": 1.0, "context": "variable_type"}, {"source": "d_bharatheeyam_books_lib_services_bookmark_service_dart", "target": "services_bookmark_service_isdarkmode", "relation": "defines", "confidence": "EXTRACTED", "confidence_score": 1.0, "source_file": "lib/services/bookmark_service.dart", "source_location": null, "weight": 1.0}, {"source": "d_bharatheeyam_books_lib_services_bookmark_service_dart", "target": "bool_get", "relation": "references", "confidence": "EXTRACTED", "confidence_score": 1.0, "source_file": "lib/services/bookmark_service.dart", "source_location": null, "weight": 1.0, "context": "variable_type"}, {"source": "d_bharatheeyam_books_lib_services_bookmark_service_dart", "target": "services_bookmark_service_fontscale", "relation": "defines", "confidence": "EXTRACTED", "confidence_score": 1.0, "source_file": "lib/services/bookmark_service.dart", "source_location": null, "weight": 1.0}, {"source": "d_bharatheeyam_books_lib_services_bookmark_service_dart", "target": "double_get", "relation": "references", "confidence": "EXTRACTED", "confidence_score": 1.0, "source_file": "lib/services/bookmark_service.dart", "source_location": null, "weight": 1.0, "context": "variable_type"}, {"source": "d_bharatheeyam_books_lib_services_bookmark_service_dart", "target": "services_bookmark_service_count", "relation": "defines", "confidence": "EXTRACTED", "confidence_score": 1.0, "source_file": "lib/services/bookmark_service.dart", "source_location": null, "weight": 1.0}, {"source": "d_bharatheeyam_books_lib_services_bookmark_service_dart", "target": "int_get", "relation": "references", "confidence": "EXTRACTED", "confidence_score": 1.0, "source_file": "lib/services/bookmark_service.dart", "source_location": null, "weight": 1.0, "context": "variable_type"}, {"source": "d_bharatheeyam_books_lib_services_bookmark_service_dart", "target": "services_bookmark_service_init", "relation": "defines", "confidence": "EXTRACTED", "confidence_score": 1.0, "source_file": "lib/services/bookmark_service.dart", "source_location": null, "weight": 1.0}, {"source": "d_bharatheeyam_books_lib_services_bookmark_service_dart", "target": "services_bookmark_service_isbookmarked", "relation": "defines", "confidence": "EXTRACTED", "confidence_score": 1.0, "source_file": "lib/services/bookmark_service.dart", "source_location": null, "weight": 1.0}, {"source": "d_bharatheeyam_books_lib_services_bookmark_service_dart", "target": "services_bookmark_service_toggle", "relation": "defines", "confidence": "EXTRACTED", "confidence_score": 1.0, "source_file": "lib/services/bookmark_service.dart", "source_location": null, "weight": 1.0}, {"source": "d_bharatheeyam_books_lib_services_bookmark_service_dart", "target": "services_bookmark_service_getsavedshlokas", "relation": "defines", "confidence": "EXTRACTED", "confidence_score": 1.0, "source_file": "lib/services/bookmark_service.dart", "source_location": null, "weight": 1.0}, {"source": "d_bharatheeyam_books_lib_services_bookmark_service_dart", "target": "services_bookmark_service_clearall", "relation": "defines", "confidence": "EXTRACTED", "confidence_score": 1.0, "source_file": "lib/services/bookmark_service.dart", "source_location": null, "weight": 1.0}, {"source": "d_bharatheeyam_books_lib_services_bookmark_service_dart", "target": "services_bookmark_service_exportasjson", "relation": "defines", "confidence": "EXTRACTED", "confidence_score": 1.0, "source_file": "lib/services/bookmark_service.dart", "source_location": null, "weight": 1.0}, {"source": "d_bharatheeyam_books_lib_services_bookmark_service_dart", "target": "services_bookmark_service_toggletheme", "relation": "defines", "confidence": "EXTRACTED", "confidence_score": 1.0, "source_file": "lib/services/bookmark_service.dart", "source_location": null, "weight": 1.0}, {"source": "d_bharatheeyam_books_lib_services_bookmark_service_dart", "target": "services_bookmark_service_setfontscale", "relation": "defines", "confidence": "EXTRACTED", "confidence_score": 1.0, "source_file": "lib/services/bookmark_service.dart", "source_location": null, "weight": 1.0}, {"source": "d_bharatheeyam_books_lib_services_bookmark_service_dart", "target": "services_bookmark_service_save", "relation": "defines", "confidence": "EXTRACTED", "confidence_score": 1.0, "source_file": "lib/services/bookmark_service.dart", "source_location": null, "weight": 1.0}, {"source": "d_bharatheeyam_books_lib_services_bookmark_service_dart", "target": "dart_convert", "relation": "imports", "confidence": "EXTRACTED", "confidence_score": 1.0, "source_file": "lib/services/bookmark_service.dart", "source_location": null, "weight": 1.0}, {"source": "d_bharatheeyam_books_lib_services_bookmark_service_dart", "target": "package_flutter_foundation_dart", "relation": "imports", "confidence": "EXTRACTED", "confidence_score": 1.0, "source_file": "lib/services/bookmark_service.dart", "source_location": null, "weight": 1.0}, {"source": "d_bharatheeyam_books_lib_services_bookmark_service_dart", "target": "package_shared_preferences_shared_preferences_dart", "relation": "imports", "confidence": "EXTRACTED", "confidence_score": 1.0, "source_file": "lib/services/bookmark_service.dart", "source_location": null, "weight": 1.0}, {"source": "d_bharatheeyam_books_lib_services_bookmark_service_dart", "target": "models_shloka_dart", "relation": "imports", "confidence": "EXTRACTED", "confidence_score": 1.0, "source_file": "lib/services/bookmark_service.dart", "source_location": null, "weight": 1.0}]}